onnx_shape_inference/__about__.py
onnx_shape_inference/__init__.py
onnx_shape_inference/_internal/shape_inference.py
onnx_shape_inference-0.0.1.dist-info/METADATA
onnx_shape_inference-0.0.1.dist-info/WHEEL
onnx_shape_inference-0.0.1.dist-info/licenses/LICENSE
onnx_shape_inference-0.0.1.dist-info/RECORD
