Metadata-Version: 2.1
Name: onnx-shape-inference
Version: 0.0.1
Summary: Symbolic shape inference for ONNX models
Project-URL: Documentation, https://github.com/justinchuby/onnx-shape-inference#readme
Project-URL: Issues, https://github.com/justinchuby/onnx-shape-inference/issues
Project-URL: Source, https://github.com/justinchuby/onnx-shape-inference
Author-email: Justin Chu <justinchuby@users.noreply.github.com>
License-Expression: MIT
License-File: LICENSE
Classifier: Development Status :: 4 - Beta
Classifier: Programming Language :: Python
Classifier: Programming Language :: Python :: 3.8
Classifier: Programming Language :: Python :: 3.9
Classifier: Programming Language :: Python :: 3.10
Classifier: Programming Language :: Python :: 3.11
Classifier: Programming Language :: Python :: Implementation :: CPython
Classifier: Programming Language :: Python :: Implementation :: PyPy
Requires-Python: >=3.8
Requires-Dist: numpy
Requires-Dist: onnx>=1.14
Requires-Dist: sympy
Requires-Dist: typing-extensions
